BioPII.py
BioPII-0.2.4.dist-info/METADATA
BioPII-0.2.4.dist-info/WHEEL
BioPII-0.2.4.dist-info/top_level.txt
BioPII-0.2.4.dist-info/RECORD
