Metadata-Version: 2.1
Name: BioPII
Version: 0.2.4
Summary: BioPII (Biology Parallel Integral Image) is a Python package for performing sliding window analysis (SWA) on biological images.
Home-page: https://github.com/OckermanSethGVSU/BioPII
Author: Seth Ockerman
Author-email: ockermas@mail.gvsu.edu
Keywords: Biology,Integral Image,Sliding Window,HPC
Classifier: License :: OSI Approved :: MIT License
Classifier: Environment :: GPU :: NVIDIA CUDA
Classifier: Intended Audience :: Science/Research
Classifier: Programming Language :: Python :: 3
Classifier: Programming Language :: Python :: 3.6
Classifier: Programming Language :: Python :: 3.7
Classifier: Programming Language :: Python :: 3.8
Requires-Dist: numpy
Requires-Dist: opencv-python
Provides-Extra: gpu-support
Requires-Dist: cupy ; extra == 'gpu-support'
